[
  {
    "all_emails": null,
    "company": "",
    "identity": null,
    "firstname": "",
    "b_year": "",
    "home": null,
    "b_month": 0,
    "py/object": "model.contact.Contact",
    "title": "",
    "email2": null,
    "phone2": null,
    "fax": null,
    "work": "",
    "address": "",
    "nickname": "",
    "all_phones_from_homepage": null,
    "b_day": 0,
    "middlename": "",
    "email3": null,
    "lastname": "",
    "email": "",
    "mobile": ""
  },
  {
    "all_emails": null,
    "company": "Roga",
    "identity": null,
    "firstname": "John",
    "b_year": "1992",
    "home": "+2343280",
    "b_month": "",
    "py/object": "model.contact.Contact",
    "title": "Lord",
    "email2": "Ema@awg.egg",
    "phone2": "+841",
    "fax": "+251636",
    "work": "+01866382",
    "address": "Moscow",
    "nickname": "NickbX8u",
    "all_phones_from_homepage": null,
    "b_day": "",
    "middlename": "",
    "email3": "",
    "lastname": "Estravee",
    "email": "Email@gert.er",
    "mobile": "+758474734"
  },
  {
    "all_emails": null,
    "company": "Co2BOgNLD",
    "identity": null,
    "firstname": "Lily",
    "b_year": "4",
    "home": "+7194255",
    "b_month": "",
    "py/object": "model.contact.Contact",
    "title": "Title8eI",
    "email2": "Email5J",
    "phone2": "+44993",
    "fax": "+5182194",
    "work": "+16",
    "address": "Moscow",
    "nickname": "NickAdhafLheS",
    "all_phones_from_homepage": null,
    "b_day": "",
    "middlename": "MNivG",
    "email3": "EmailXnqUq3R",
    "lastname": "Brooks",
    "email": "Email1Y",
    "mobile": "+852424235"
  },
  {
    "all_emails": null,
    "company": "CoYda1",
    "identity": null,
    "firstname": "Brian",
    "b_year": "474",
    "home": "+13391589",
    "b_month": "",
    "py/object": "model.contact.Contact",
    "title": "TitlemUFYIXg",
    "email2": "EmailYeO",
    "phone2": "+233343443",
    "fax": "+66572",
    "work": "+4438443527",
    "address": "MoscowLxa",
    "nickname": "NickUmtd",
    "all_phones_from_homepage": null,
    "b_day": "",
    "middlename": "MN",
    "email3": "Emailn",
    "lastname": "Korchse",
    "email": "Email9",
    "mobile": "+0972454"
  },
  {
    "all_emails": null,
    "company": "Co7",
    "identity": null,
    "firstname": "Flyer",
    "b_year": "751",
    "home": "+928",
    "b_month": "",
    "py/object": "model.contact.Contact",
    "title": "Title",
    "email2": "EmailSbFmsKy0I",
    "phone2": "+2",
    "fax": "+9515766725",
    "work": "+28",
    "address": "Moscow0M6bG",
    "nickname": "NickBxUsLhYZ",
    "all_phones_from_homepage": null,
    "b_day": "",
    "middlename": "theresabigname",
    "email3": "EmailpW",
    "lastname": "Portus",
    "email": "portus@gmail.com",
    "mobile": "+0666883"
  },
  {
    "all_emails": null,
    "company": "Co7I50K",
    "identity": null,
    "firstname": "FN",
    "b_year": "380",
    "home": "+747366",
    "b_month": "",
    "py/object": "model.contact.Contact",
    "title": "TitlePHHeCvV4",
    "email2": "EmailuqVhZ",
    "phone2": "+44735",
    "fax": "+874",
    "work": "+2349136293",
    "address": "MoscowzL",
    "nickname": "Nickqsdf",
    "all_phones_from_homepage": null,
    "b_day": "",
    "middlename": "M890",
    "email3": "Emailv51s",
    "lastname": "Breeven",
    "email": "EmailCr",
    "mobile": "+562912"
  }
]